{
  "$schema": "https://ui.shadcn.com/schema/registry-item.json",
  "name": "theme",
  "type": "registry:theme",
  "title": "Domino theme",
  "description": "Domino theme",
  "files": [
    {
      "path": "app/globals.css",
      "content": "@import \"tailwindcss\";\n@import \"tw-animate-css\";\n\n@custom-variant dark (&:is(.dark *));\n\n@theme inline {\n  --color-background: var(--background);\n  --color-foreground: var(--foreground);\n  --font-sans: var(--font-inter-sans);\n  --font-mono: var(--font-geist-mono);\n  --color-sidebar-ring: var(--sidebar-ring);\n  --color-sidebar-border: var(--sidebar-border);\n  --color-sidebar-accent-foreground: var(--sidebar-accent-foreground);\n  --color-sidebar-accent: var(--sidebar-accent);\n  --color-sidebar-primary-foreground: var(--sidebar-primary-foreground);\n  --color-sidebar-primary: var(--sidebar-primary);\n  --color-sidebar-foreground: var(--sidebar-foreground);\n  --color-sidebar: var(--sidebar);\n  --color-chart-5: var(--chart-5);\n  --color-chart-4: var(--chart-4);\n  --color-chart-3: var(--chart-3);\n  --color-chart-2: var(--chart-2);\n  --color-chart-1: var(--chart-1);\n  --color-ring: var(--ring);\n  --color-input: var(--input);\n  --color-border: var(--border);\n  --color-destructive: var(--destructive);\n  --color-accent-foreground: var(--accent-foreground);\n  --color-accent: var(--accent);\n  --color-muted-foreground: var(--muted-foreground);\n  --color-muted: var(--muted);\n  --color-secondary-foreground: var(--secondary-foreground);\n  --color-secondary: var(--secondary);\n  --color-primary-foreground: var(--primary-foreground);\n  --color-primary: var(--primary);\n  --color-popover-foreground: var(--popover-foreground);\n  --color-popover: var(--popover);\n  --color-card-foreground: var(--card-foreground);\n  --color-card: var(--card);\n  --radius-sm: calc(var(--radius) - 4px);\n  --radius-md: calc(var(--radius) - 2px);\n  --radius-lg: var(--radius);\n  --radius-xl: calc(var(--radius) + 4px);\n}\n\n:root {\n  --radius: 0.625rem;\n  --card: oklch(1 0 0);\n  --card-foreground: oklch(0.145 0 0);\n  --popover: oklch(1 0 0);\n  --popover-foreground: oklch(0.145 0 0);\n  --primary: oklch(0.4744 0.256 297.4098);\n  --primary-foreground: oklch(1 0 0);\n  --secondary: oklch(0.97 0 0);\n  --secondary-foreground: oklch(0.205 0 0);\n  --muted: oklch(0.97 0 0);\n  --muted-foreground: oklch(0.556 0 0);\n  --accent: oklch(0.97 0 0);\n  --accent-foreground: oklch(0.205 0 0);\n  --destructive: oklch(0.577 0.245 27.325);\n  --destructive-foreground: oklch(1 0 0);\n  --border: oklch(0.922 0 0);\n  --input: oklch(0.922 0 0);\n  --ring: oklch(0.708 0 0);\n  --chart-1: oklch(0.646 0.222 41.116);\n  --chart-2: oklch(0.6 0.118 184.704);\n  --chart-3: oklch(0.398 0.07 227.392);\n  --chart-4: oklch(0.828 0.189 84.429);\n  --chart-5: oklch(0.769 0.188 70.08);\n  --sidebar: oklch(0.985 0 0);\n  --sidebar-foreground: oklch(0.145 0 0);\n  --sidebar-primary: oklch(0.205 0 0);\n  --sidebar-primary-foreground: oklch(0.985 0 0);\n  --sidebar-accent: oklch(0.97 0 0);\n  --sidebar-accent-foreground: oklch(0.205 0 0);\n  --sidebar-border: oklch(0.922 0 0);\n  --sidebar-ring: oklch(0.708 0 0);\n  --surface: var(--background);\n  --surface-foreground: var(--foreground);\n  --code: var(--surface);\n  --code-foreground: var(--surface-foreground);\n  --code-highlight: oklch(0.96 0 0);\n  --code-number: oklch(0.56 0 0);\n  --selection: oklch(0.145 0 0);\n  --selection-foreground: oklch(1 0 0);\n  --background: oklch(1 0 0);\n  --foreground: oklch(0.145 0 0);\n}\n\n.dark {\n  --background: oklch(0.145 0 0);\n  --foreground: oklch(0.985 0 0);\n  --card: oklch(0.205 0 0);\n  --card-foreground: oklch(0.985 0 0);\n  --popover: oklch(0.205 0 0);\n  --popover-foreground: oklch(0.985 0 0);\n  --primary: oklch(0.922 0 0);\n  --primary-foreground: oklch(0.205 0 0);\n  --secondary: oklch(0.269 0 0);\n  --secondary-foreground: oklch(0.985 0 0);\n  --muted: oklch(0.269 0 0);\n  --muted-foreground: oklch(0.708 0 0);\n  --accent: oklch(0.269 0 0);\n  --accent-foreground: oklch(0.985 0 0);\n  --destructive: oklch(0.704 0.191 22.216);\n  --border: oklch(1 0 0 / 10%);\n  --input: oklch(1 0 0 / 15%);\n  --ring: oklch(0.556 0 0);\n  --chart-1: oklch(0.488 0.243 264.376);\n  --chart-2: oklch(0.696 0.17 162.48);\n  --chart-3: oklch(0.769 0.188 70.08);\n  --chart-4: oklch(0.627 0.265 303.9);\n  --chart-5: oklch(0.645 0.246 16.439);\n  --sidebar: oklch(0.205 0 0);\n  --sidebar-foreground: oklch(0.985 0 0);\n  --sidebar-primary: oklch(0.488 0.243 264.376);\n  --sidebar-primary-foreground: oklch(0.985 0 0);\n  --sidebar-accent: oklch(0.269 0 0);\n  --sidebar-accent-foreground: oklch(0.985 0 0);\n  --sidebar-border: oklch(1 0 0 / 10%);\n  --sidebar-ring: oklch(0.556 0 0);\n  --surface: var(--background);\n  --surface-foreground: var(--foreground);\n  --code: var(--surface);\n  --code-foreground: var(--surface-foreground);\n  --code-highlight: oklch(0.27 0 0);\n  --code-number: oklch(0.72 0 0);\n  --selection: oklch(0.922 0 0);\n  --selection-foreground: oklch(0.205 0 0);\n}\n\n@layer base {\n  * {\n    @apply border-border outline-ring/50;\n  }\n  body {\n    @apply bg-background text-foreground;\n  }\n}\n",
      "type": "registry:style",
      "target": "app/globals.css"
    },
    {
      "path": "postcss.config.mjs",
      "content": "const config = {\n  plugins: [\"@tailwindcss/postcss\"],\n};\n\nexport default config;\n",
      "type": "registry:file",
      "target": "postcss.config.mjs"
    }
  ],
  "cssVars": {
    "light": {
      "radius": "0.625rem",
      "card": "oklch(1 0 0)",
      "card-foreground": "oklch(0.145 0 0)",
      "popover": "oklch(1 0 0)",
      "popover-foreground": "oklch(0.145 0 0)",
      "primary": "oklch(0.4744 0.256 297.4098)",
      "primary-foreground": "oklch(1 0 0)",
      "secondary": "oklch(0.97 0 0)",
      "secondary-foreground": "oklch(0.205 0 0)",
      "muted": "oklch(0.97 0 0)",
      "muted-foreground": "oklch(0.556 0 0)",
      "accent": "oklch(0.97 0 0)",
      "accent-foreground": "oklch(0.205 0 0)",
      "destructive": "oklch(0.577 0.245 27.325)",
      "destructive-foreground": "oklch(1 0 0)",
      "border": "oklch(0.922 0 0)",
      "input": "oklch(0.922 0 0)",
      "ring": "oklch(0.708 0 0)",
      "chart-1": "oklch(0.646 0.222 41.116)",
      "chart-2": "oklch(0.6 0.118 184.704)",
      "chart-3": "oklch(0.398 0.07 227.392)",
      "chart-4": "oklch(0.828 0.189 84.429)",
      "chart-5": "oklch(0.769 0.188 70.08)",
      "sidebar": "oklch(0.985 0 0)",
      "sidebar-foreground": "oklch(0.145 0 0)",
      "sidebar-primary": "oklch(0.205 0 0)",
      "sidebar-primary-foreground": "oklch(0.985 0 0)",
      "sidebar-accent": "oklch(0.97 0 0)",
      "sidebar-accent-foreground": "oklch(0.205 0 0)",
      "sidebar-border": "oklch(0.922 0 0)",
      "sidebar-ring": "oklch(0.708 0 0)",
      "surface": "var(--background)",
      "surface-foreground": "var(--foreground)",
      "code": "var(--surface)",
      "code-foreground": "var(--surface-foreground)",
      "code-highlight": "oklch(0.96 0 0)",
      "code-number": "oklch(0.56 0 0)",
      "selection": "oklch(0.145 0 0)",
      "selection-foreground": "oklch(1 0 0)",
      "background": "oklch(1 0 0)",
      "foreground": "oklch(0.145 0 0)"
    },
    "dark": {
      "background": "oklch(0.145 0 0)",
      "foreground": "oklch(0.985 0 0)",
      "card": "oklch(0.205 0 0)",
      "card-foreground": "oklch(0.985 0 0)",
      "popover": "oklch(0.205 0 0)",
      "popover-foreground": "oklch(0.985 0 0)",
      "primary": "oklch(0.922 0 0)",
      "primary-foreground": "oklch(0.205 0 0)",
      "secondary": "oklch(0.269 0 0)",
      "secondary-foreground": "oklch(0.985 0 0)",
      "muted": "oklch(0.269 0 0)",
      "muted-foreground": "oklch(0.708 0 0)",
      "accent": "oklch(0.269 0 0)",
      "accent-foreground": "oklch(0.985 0 0)",
      "destructive": "oklch(0.704 0.191 22.216)",
      "border": "oklch(1 0 0 / 10%)",
      "input": "oklch(1 0 0 / 15%)",
      "ring": "oklch(0.556 0 0)",
      "chart-1": "oklch(0.488 0.243 264.376)",
      "chart-2": "oklch(0.696 0.17 162.48)",
      "chart-3": "oklch(0.769 0.188 70.08)",
      "chart-4": "oklch(0.627 0.265 303.9)",
      "chart-5": "oklch(0.645 0.246 16.439)",
      "sidebar": "oklch(0.205 0 0)",
      "sidebar-foreground": "oklch(0.985 0 0)",
      "sidebar-primary": "oklch(0.488 0.243 264.376)",
      "sidebar-primary-foreground": "oklch(0.985 0 0)",
      "sidebar-accent": "oklch(0.269 0 0)",
      "sidebar-accent-foreground": "oklch(0.985 0 0)",
      "sidebar-border": "oklch(1 0 0 / 10%)",
      "sidebar-ring": "oklch(0.556 0 0)",
      "surface": "var(--background)",
      "surface-foreground": "var(--foreground)",
      "code": "var(--surface)",
      "code-foreground": "var(--surface-foreground)",
      "code-highlight": "oklch(0.27 0 0)",
      "code-number": "oklch(0.72 0 0)",
      "selection": "oklch(0.922 0 0)",
      "selection-foreground": "oklch(0.205 0 0)"
    }
  }
}